particle/__init__.py
particle/__main__.py
particle/exceptions.py
particle/py.typed
particle/shared_literals.py
particle/typing.py
particle/version.py
particle/version.pyi
particle/_compat/__init__.py
particle/_compat/typing.py
particle/converters/__init__.py
particle/converters/bimap.py
particle/converters/corsika.py
particle/converters/evtgen.py
particle/converters/geant.py
particle/converters/py.typed
particle/converters/pythia.py
particle/corsika/__init__.py
particle/corsika/corsika7id.py
particle/data/README.rst
particle/data/__init__.py
particle/data/conversions.csv
particle/data/mass_width_2008.fwf
particle/data/mass_width_2008_ext.fwf
particle/data/mass_width_2022.mcd
particle/data/mass_width_2023.mcd
particle/data/mass_width_2024.mcd
particle/data/mass_width_2025.mcd
particle/data/nuclei2020.csv
particle/data/nuclei2022.csv
particle/data/particle2022.csv
particle/data/particle2023.csv
particle/data/particle2024.csv
particle/data/particle2025.csv
particle/data/pdgid_to_corsika7id.csv
particle/data/pdgid_to_evtgenname.csv
particle/data/pdgid_to_geant3id.csv
particle/data/pdgid_to_latexname.csv
particle/data/pdgid_to_pythiaid.csv
particle/data/py.typed
particle/geant/__init__.py
particle/geant/geant3id.py
particle/geant/py.typed
particle/lhcb/__init__.py
particle/lhcb/converters.py
particle/lhcb/functions.py
particle/lhcb/py.typed
particle/lhcb/data/__init__.py
particle/lhcb/data/pdgid_to_lhcbname.csv
particle/lhcb/data/py.typed
particle/particle/__init__.py
particle/particle/convert.py
particle/particle/enums.py
particle/particle/kinematics.py
particle/particle/literals.py
particle/particle/particle.py
particle/particle/py.typed
particle/particle/regex.py
particle/particle/utilities.py
particle/pdgid/__init__.py
particle/pdgid/functions.py
particle/pdgid/literals.py
particle/pdgid/pdgid.py
particle/pdgid/py.typed
particle/pythia/__init__.py
particle/pythia/py.typed
particle/pythia/pythiaid.py
particle-0.26.1.dist-info/METADATA
particle-0.26.1.dist-info/WHEEL
particle-0.26.1.dist-info/licenses/LICENSE
particle-0.26.1.dist-info/RECORD
