Metadata-Version: 2.4
Name: particle
Version: 0.26.1
Summary: Extended PDG particle data and MC identification codes
Project-URL: Homepage, https://github.com/scikit-hep/particle
Author-email: Eduardo Rodrigues <eduardo.rodrigues@cern.ch>, Henry Schreiner <henryfs@princeton.edu>
Maintainer-email: Scikit-HEP <scikit-hep-admins@googlegroups.com>
License-Expression: BSD-3-Clause
License-File: LICENSE
Keywords: HEP,MC identification codes,PDG,PDGID,particle,particle data table,particle properties
Classifier: Development Status :: 5 - Production/Stable
Classifier: Intended Audience :: Developers
Classifier: Intended Audience :: Science/Research
Classifier: Operating System :: OS Independent
Classifier: Programming Language :: Python
Classifier: Programming Language :: Python :: 3
Classifier: Programming Language :: Python :: 3 :: Only
Classifier: Programming Language :: Python :: 3.9
Classifier: Programming Language :: Python :: 3.10
Classifier: Programming Language :: Python :: 3.11
Classifier: Programming Language :: Python :: 3.12
Classifier: Programming Language :: Python :: 3.13
Classifier: Programming Language :: Python :: 3.14
Classifier: Topic :: Scientific/Engineering
Requires-Python: >=3.9
Requires-Dist: attrs>=22.2.0
Requires-Dist: hepunits>=2.4.0
Requires-Dist: typing-extensions>=4.5; python_version < '3.13'
Provides-Extra: all
Requires-Dist: pandas; extra == 'all'
Requires-Dist: pre-commit; extra == 'all'
Requires-Dist: pytest-benchmark; extra == 'all'
Requires-Dist: pytest-cov; extra == 'all'
Requires-Dist: pytest>=6; extra == 'all'
Requires-Dist: tabulate; extra == 'all'
Provides-Extra: dev
Requires-Dist: pandas; extra == 'dev'
Requires-Dist: pre-commit; extra == 'dev'
Requires-Dist: pytest-benchmark; extra == 'dev'
Requires-Dist: pytest>=6; extra == 'dev'
Requires-Dist: tabulate; extra == 'dev'
Provides-Extra: test
Requires-Dist: pandas; extra == 'test'
Requires-Dist: pytest-benchmark; extra == 'test'
Requires-Dist: pytest-cov; extra == 'test'
Requires-Dist: pytest>=6; extra == 'test'
Requires-Dist: tabulate; extra == 'test'
